ordway/__init__.py
ordway/__version__.py
ordway/client.py
ordway/consts.py
ordway/exceptions.py
ordway/session.py
ordway/utils.py
ordway/api/__init__.py
ordway/api/base.py
ordway/api/endpoints.py
ordway/api/exceptions.py
ordway-0.5.2.dist-info/LICENSE
ordway-0.5.2.dist-info/METADATA
ordway-0.5.2.dist-info/WHEEL
ordway-0.5.2.dist-info/top_level.txt
ordway-0.5.2.dist-info/RECORD
