Metadata-Version: 2.1
Name: ordway
Version: 0.5.2
Summary: A simple Ordway API wrapper.
Home-page: https://github.com/efnineio/ordway
Author: Geoffrey Doempke
Author-email: nicholas@logram.io
License: UNKNOWN
Project-URL: Documentation, https://github.com/efnineio/ordway/blob/master/README.md
Project-URL: Source, https://github.com/efnineio/ordway
Project-URL: Tracker, https://github.com/efnineio/ordway/issues
Project-URL: Changelog, https://github.com/efnineio/ordway/blob/master/CHANGES.md
Keywords: ordway api wrapper
Platform: UNKNOWN
Classifier: Development Status :: 2 - Pre-Alpha
Classifier: Environment :: Other Environment
Classifier: Intended Audience :: Developers
Classifier: License :: OSI Approved :: MIT License
Classifier: Natural Language :: English
Classifier: Operating System :: OS Independent
Classifier: Programming Language :: Python :: 3 :: Only
Classifier: Programming Language :: Python :: 3.6
Classifier: Programming Language :: Python :: 3.7
Classifier: Programming Language :: Python :: 3.8
Classifier: Topic :: Software Development :: Libraries
Classifier: Topic :: Utilities
Requires-Python: >=3.6
License-File: LICENSE
Requires-Dist: requests (==2.24.0)
Provides-Extra: testing
Requires-Dist: tox (==3.17.1) ; extra == 'testing'
